fluidfft/__init__.py
fluidfft/_version.py
fluidfft/base.py
fluidfft/bench.py
fluidfft/bench_analysis.py
fluidfft/build_conf.txt
fluidfft/cli_get_methods.py
fluidfft/util.py
fluidfft/fft2d/__init__.py
fluidfft/fft2d/operators.py
fluidfft/fft2d/testing.py
fluidfft/fft2d/with_dask.py
fluidfft/fft2d/with_pyfftw.py
fluidfft/fft2d/__numba__/operators.py
fluidfft/fft2d/__python__/operators.py
fluidfft/fft2d/__pythran__/operators.cpython-313-aarch64-linux-gnu.so
fluidfft/fft3d/__init__.py
fluidfft/fft3d/base.py
fluidfft/fft3d/operators.py
fluidfft/fft3d/testing.py
fluidfft/fft3d/with_pyfftw.py
fluidfft/fft3d/__numba__/operators.py
fluidfft/fft3d/__python__/operators.py
fluidfft/fft3d/__pythran__/operators.cpython-313-aarch64-linux-gnu.so
fluidfft-0.4.5.dist-info/METADATA
fluidfft-0.4.5.dist-info/WHEEL
fluidfft-0.4.5.dist-info/entry_points.txt
fluidfft-0.4.5.dist-info/RECORD
fluidfft-0.4.5.dist-info/licenses/LICENSE.txt
