Metadata-Version: 2.4
Name: fluidfft
Version: 0.4.5
Summary: Efficient and easy Fast Fourier Transform (FFT) for Python.
Keywords: Fast Fourier Transform,FFT,spectral code
Author-Email: Pierre Augier <pierre.augier@legi.cnrs.fr>
License-Expression: CECILL-1.0
License-File: LICENSE.txt
Classifier: Development Status :: 5 - Production/Stable
Classifier: Intended Audience :: Education
Classifier: Intended Audience :: Science/Research
Classifier: Programming Language :: C
Classifier: Programming Language :: Cython
Classifier: Programming Language :: Python
Classifier: Programming Language :: Python :: 3
Classifier: Programming Language :: Python :: 3.10
Classifier: Programming Language :: Python :: 3.11
Classifier: Programming Language :: Python :: 3.12
Classifier: Programming Language :: Python :: 3.13
Classifier: Programming Language :: Python :: 3.14
Classifier: Topic :: Scientific/Engineering
Project-URL: Homepage, https://foss.heptapod.net/fluiddyn/fluidfft
Requires-Python: >=3.11
Requires-Dist: fluiddyn>=0.2.3
Requires-Dist: transonic>=0.6.4
Provides-Extra: pyfftw
Requires-Dist: pyfftw>=0.10.4; extra == "pyfftw"
Provides-Extra: dask
Requires-Dist: dask; extra == "dask"
Provides-Extra: mpi
Requires-Dist: mpi4py; extra == "mpi"
Provides-Extra: fftw
Requires-Dist: fluidfft-fftw; extra == "fftw"
Provides-Extra: mpi-with-fftw
Requires-Dist: fluidfft-mpi_with_fftw; extra == "mpi-with-fftw"
Provides-Extra: fftwmpi
Requires-Dist: fluidfft-fftwmpi; extra == "fftwmpi"
Provides-Extra: pfft
Requires-Dist: fluidfft-pfft; extra == "pfft"
Provides-Extra: p3dfft
Requires-Dist: fluidfft-p3dfft; extra == "p3dfft"
